<?xml version="1.0" encoding="utf-8"?>
<Noticia codigo="dde8f8c1-6485-432f-9837-e7098c19610e">
  <Categoria><![CDATA[Finanças]]></Categoria>
  <Origem>28</Origem>
  <Data>07/08/2024</Data>
  <Link>https://valor.globo.com/financas/noticia/2024/08/07/dolar-recua-com-alivio-no-exterior-apos-sinalizacao-do-bc-do-japao.ghtml</Link>
  <Procedencia>Gabriel Caldeira</Procedencia>
  <Manchete><![CDATA[Dólar recua com alívio no exterior após sinalização do BC do Japão]]></Manchete>
  <Texto><![CDATA[ dólar encerrou a sessão desta quarta-feira em queda, apoiado pelo movimento global de retomada de risco após o vice-presidente do Banco do Japão (BoJ), Shinichi Uchida, afirmar que a autoridade monetária não subirá juros em meio à “instabilidade” dos mercados. Ainda que parte do bom humor tenha se dissipado ao longo da tarde, o real e outras moedas de países emergentes ainda encontraram fôlego para se valorizar hoje.


O dólar à vista fechou em queda de 0,55%, cotado a R$ 5,6249, após tocar a máxima intradiária de R$ 5,6405 e a mínima de R$ 5,5977. O euro comercial recuou 0,63%, a R$ 6,1434.


No exterior, por volta de 17h10, o índice DXY do dólar subia 0,22%, a 103,196 pontos, puxado pela forte alta da moeda americana sobre o iene, de cerca de 1,5%. O dólar, em contrapartida, recuava ante pares do real: a divisa anotava baixa de 1,64% contra o peso mexicano; tinha leve baixa de 0,08% ante o peso chileno; e recuava 0,52% no confronto com o rand sul-africano.
]]></Texto>
  <idioma><![CDATA[Português]]></idioma>
  <DataEnvio>07/08/2024</DataEnvio>
</Noticia>